cli.py
playlist_stitcher-0.1.0.dist-info/LICENSE
playlist_stitcher-0.1.0.dist-info/METADATA
playlist_stitcher-0.1.0.dist-info/WHEEL
playlist_stitcher-0.1.0.dist-info/entry_points.txt
playlist_stitcher-0.1.0.dist-info/top_level.txt
playlist_stitcher-0.1.0.dist-info/RECORD
