Metadata-Version: 2.1
Name: playlist-stitcher
Version: 0.1.0
Summary: A tool to download and stitch YouTube playlists
Home-page: https://github.com/you-tools/playlist-stitcher
Author: Chen Stanilovsky
Author-email: chen.stanilovsky@gmail.com
License: GNU GPLv3
Classifier: Programming Language :: Python :: 3.11
Classifier: Operating System :: OS Independent
Requires-Python: >=3.11
License-File: LICENSE
Requires-Dist: click ~=8.1
Requires-Dist: pytube ~=15.0
Requires-Dist: moviepy ~=1.0.3
